[
  {
    "name": "\nCodeforces Round #816 (Div. 2)\n    ",
    "time": "Aug/20/2022 17:35",
    "duration": "02:00",
    "toStart": "Before start 36:29:36",
    "toRegister": "Register »\n x6730\n                    Until closing 36:24:36\n                        *has extra registration",
    "link": "https://codeforces.com/contests",
    "codePrevUpd": 1660874724679
  },
  {
    "name": "\nCodeforces Round (Div. 2)\n    ",
    "time": "Sep/02/2022 17:35",
    "duration": "02:00",
    "toStart": "Before start 2 weeks",
    "toRegister": "Before registration\n                        13 days",
    "link": "https://codeforces.com/contests",
    "codePrevUpd": 1660874724679
  }
]